about.py
cdk_chalice.py
cdk_chalice-0.9.0.dist-info/LICENSE
cdk_chalice-0.9.0.dist-info/METADATA
cdk_chalice-0.9.0.dist-info/WHEEL
cdk_chalice-0.9.0.dist-info/top_level.txt
cdk_chalice-0.9.0.dist-info/RECORD
